pgmpy/__init__.py
pgmpy/global_vars.py
pgmpy/base/DAG.py
pgmpy/base/UndirectedGraph.py
pgmpy/base/__init__.py
pgmpy/estimators/BayesianEstimator.py
pgmpy/estimators/CITests.py
pgmpy/estimators/EM.py
pgmpy/estimators/ExhaustiveSearch.py
pgmpy/estimators/ExpertKnowledge.py
pgmpy/estimators/GES.py
pgmpy/estimators/HillClimbSearch.py
pgmpy/estimators/LinearModel.py
pgmpy/estimators/MLE.py
pgmpy/estimators/MirrorDescentEstimator.py
pgmpy/estimators/MmhcEstimator.py
pgmpy/estimators/PC.py
pgmpy/estimators/SEMEstimator.py
pgmpy/estimators/ScoreCache.py
pgmpy/estimators/StructureScore.py
pgmpy/estimators/TreeSearch.py
pgmpy/estimators/__init__.py
pgmpy/estimators/base.py
pgmpy/estimators/expert.py
pgmpy/extern/__init__.py
pgmpy/extern/tabulate.py
pgmpy/factors/FactorDict.py
pgmpy/factors/FactorSet.py
pgmpy/factors/__init__.py
pgmpy/factors/base.py
pgmpy/factors/continuous/LinearGaussianCPD.py
pgmpy/factors/continuous/__init__.py
pgmpy/factors/discrete/CPD.py
pgmpy/factors/discrete/DiscreteFactor.py
pgmpy/factors/discrete/JointProbabilityDistribution.py
pgmpy/factors/discrete/NoisyOR.py
pgmpy/factors/discrete/__init__.py
pgmpy/factors/hybrid/FunctionalCPD.py
pgmpy/factors/hybrid/__init__.py
pgmpy/independencies/Independencies.py
pgmpy/independencies/__init__.py
pgmpy/inference/ApproxInference.py
pgmpy/inference/CausalInference.py
pgmpy/inference/EliminationOrder.py
pgmpy/inference/ExactInference.py
pgmpy/inference/__init__.py
pgmpy/inference/base.py
pgmpy/inference/dbn_inference.py
pgmpy/inference/mplp.py
pgmpy/metrics/__init__.py
pgmpy/metrics/bn_inference.py
pgmpy/metrics/metrics.py
pgmpy/models/BayesianNetwork.py
pgmpy/models/ClusterGraph.py
pgmpy/models/DiscreteBayesianNetwork.py
pgmpy/models/DynamicBayesianNetwork.py
pgmpy/models/FactorGraph.py
pgmpy/models/JunctionTree.py
pgmpy/models/LinearGaussianBayesianNetwork.py
pgmpy/models/MarkovChain.py
pgmpy/models/MarkovNetwork.py
pgmpy/models/NaiveBayes.py
pgmpy/models/SEM.py
pgmpy/models/__init__.py
pgmpy/readwrite/BIF.py
pgmpy_no_torch-1.0.4.dist-info/licenses/AUTHORS.rst
pgmpy_no_torch-1.0.4.dist-info/licenses/LICENSE
pgmpy_no_torch-1.0.4.dist-info/METADATA
pgmpy_no_torch-1.0.4.dist-info/WHEEL
pgmpy_no_torch-1.0.4.dist-info/top_level.txt
pgmpy_no_torch-1.0.4.dist-info/RECORD
