Metadata-Version: 2.4
Name: pgmpy-no-torch
Version: 1.0.4
Summary: A library for Probabilistic Graphical Models
Home-page: https://github.com/pgmpy/pgmpy
Author: Ankur Ankan
Author-email: ankurankan@gmail.com
License: MIT
Classifier: Programming Language :: Python :: 3.10
Classifier: Programming Language :: Python :: 3.11
Classifier: Programming Language :: Python :: 3.12
Classifier: Programming Language :: Python :: 3.13
Classifier: Intended Audience :: Education
Classifier: Intended Audience :: Science/Research
Classifier: Operating System :: Unix
Classifier: Operating System :: Microsoft :: Windows
Classifier: Operating System :: MacOS
Classifier: Topic :: Scientific/Engineering
Classifier: Topic :: Scientific/Engineering :: Artificial Intelligence
Classifier: Topic :: Scientific/Engineering :: Bio-Informatics
License-File: LICENSE
License-File: AUTHORS.rst
Requires-Dist: networkx
Requires-Dist: numpy
Requires-Dist: scipy
Requires-Dist: scikit-learn
Requires-Dist: pandas
Requires-Dist: statsmodels
Requires-Dist: tqdm
Requires-Dist: joblib
Requires-Dist: opt_einsum
Provides-Extra: all
Requires-Dist: networkx; extra == "all"
Requires-Dist: numpy; extra == "all"
Requires-Dist: scipy; extra == "all"
Requires-Dist: scikit-learn; extra == "all"
Requires-Dist: pandas; extra == "all"
Requires-Dist: statsmodels; extra == "all"
Requires-Dist: tqdm; extra == "all"
Requires-Dist: joblib; extra == "all"
Requires-Dist: opt_einsum; extra == "all"
Requires-Dist: xdoctest; extra == "all"
Requires-Dist: pytest; extra == "all"
Requires-Dist: pytest-cov; extra == "all"
Requires-Dist: pytest-xdist; extra == "all"
Requires-Dist: coverage; extra == "all"
Requires-Dist: mock; extra == "all"
Requires-Dist: black; extra == "all"
Requires-Dist: pre-commit; extra == "all"
Requires-Dist: daft-pgm; extra == "all"
Requires-Dist: xgboost; extra == "all"
Requires-Dist: litellm; extra == "all"
Requires-Dist: pyparsing; extra == "all"
Provides-Extra: optional
Requires-Dist: daft-pgm; extra == "optional"
Requires-Dist: xgboost; extra == "optional"
Requires-Dist: litellm; extra == "optional"
Requires-Dist: pyparsing; extra == "optional"
Provides-Extra: tests
Requires-Dist: xdoctest; extra == "tests"
Requires-Dist: pytest; extra == "tests"
Requires-Dist: pytest-cov; extra == "tests"
Requires-Dist: pytest-xdist; extra == "tests"
Requires-Dist: coverage; extra == "tests"
Requires-Dist: mock; extra == "tests"
Requires-Dist: black; extra == "tests"
Requires-Dist: pre-commit; extra == "tests"
Dynamic: author
Dynamic: author-email
Dynamic: classifier
Dynamic: description
Dynamic: description-content-type
Dynamic: home-page
Dynamic: license
Dynamic: license-file
Dynamic: provides-extra
Dynamic: requires-dist
Dynamic: summary
